yt_rank_checker/__init__.py
yt_rank_checker/utils.py
yt_rank_checker/yt_rank.py
yt_rank_checker-1.0.1.dist-info/LICENSE.txt
yt_rank_checker-1.0.1.dist-info/METADATA
yt_rank_checker-1.0.1.dist-info/WHEEL
yt_rank_checker-1.0.1.dist-info/top_level.txt
yt_rank_checker-1.0.1.dist-info/RECORD
