Metadata-Version: 2.1
Name: yt-rank-checker
Version: 1.0.1
Summary: Find where videos rank on YouTube by keywords for a youtube channel
Home-page: UNKNOWN
Author: Renaissance Troll
Author-email: troll@renaissancetroll.com
License: LICENSE.txt
Platform: UNKNOWN
Requires-Dist: arrow (==0.12.1)
Requires-Dist: selenium (==3.12)
Requires-Dist: pyecharts (==1.0.0)
